dsw_engine_gateway-1.0.1.dist-info/licenses/LICENSE
engine_gateway/__init__.py
engine_gateway/app.py
engine_gateway/build_info.py
engine_gateway/config.py
engine_gateway/consts.py
engine_gateway/logic.py
engine_gateway/schemas.py
engine_gateway/sentry.py
dsw_engine_gateway-1.0.1.dist-info/METADATA
dsw_engine_gateway-1.0.1.dist-info/WHEEL
dsw_engine_gateway-1.0.1.dist-info/top_level.txt
dsw_engine_gateway-1.0.1.dist-info/RECORD
