Metadata-Version: 2.4
Name: dsw-engine-gateway
Version: 1.0.1
Summary: Framework for services around DSW
Author-email: Marek Suchánek <marek.suchanek@ds-wizard.org>
License: Apache-2.0
Project-URL: Homepage, https://ds-wizard.org
Keywords: wizard,gateway,app,api,services
Classifier: Development Status :: 5 - Production/Stable
Classifier: Intended Audience :: Developers
Classifier: License :: OSI Approved :: Apache Software License
Classifier: Operating System :: OS Independent
Classifier: Programming Language :: Python
Classifier: Programming Language :: Python :: 3.13
Requires-Python: <4,>=3.13
License-File: LICENSE
Requires-Dist: fastapi<1.0,>=0.120
Requires-Dist: PyYAML<7.0,>=6.0
Requires-Dist: sentry-sdk<3.0.0,>=2.44.0
Dynamic: license-file
